dlt_source_morphais/__init__.py
dlt_source_morphais/rest_client.py
dlt_source_morphais/settings.py
dlt_source_morphais/type_adapters.py
dlt_source_morphais/model/__init__.py
dlt_source_morphais/model/current_python_major_minor.py
dlt_source_morphais/model/spec.py
dlt_source_morphais/model/tests/__init__.py
dlt_source_morphais/model/tests/test_my_spec.py
dlt_source_morphais/tests/__init__.py
dlt_source_morphais-0.0.5.dist-info/LICENSE
dlt_source_morphais-0.0.5.dist-info/METADATA
dlt_source_morphais-0.0.5.dist-info/WHEEL
dlt_source_morphais-0.0.5.dist-info/top_level.txt
dlt_source_morphais-0.0.5.dist-info/RECORD
