Metadata-Version: 2.2
Name: dlt-source-morphais
Version: 0.0.5
Summary: A DLT source for Morphais
Author: Planet A GmbH
Author-email: dev@planet-a.com
Classifier: Programming Language :: Python :: 3.12
Classifier: License :: OSI Approved :: MIT License
Classifier: Operating System :: OS Independent
Requires-Python: >=3.12
License-File: LICENSE
Requires-Dist: dlt>=1.8.0
Provides-Extra: show
Requires-Dist: dlt[duckdb]>=1.8.0; extra == "show"
Requires-Dist: streamlit>=1.41.1; extra == "show"
Requires-Dist: watchdog>=6.0.0; extra == "show"
Dynamic: author
Dynamic: author-email
Dynamic: classifier
Dynamic: summary
